lexi_bu/.lexi_data/20241114_LEXIAngleData_20250302Landing_rad.csv
lexi_bu/.lexi_data/GMP1_MEAS_CBI-data-2024-11-07 16_20_24.csv
lexi_bu/.lexi_data/LEXI_RA_DEC_J2000_rad-data-2024-11-07 16_20_24.csv
lexi_bu/.lexi_data/all_lexi_file_list.csv
lexi_bu/.lexi_data/file_list.csv
lexi_bu/.lexi_data/sample_lexi_pointing_ephem_edited.csv
lexi_bu/.lexi_data/sample_xray_background.csv
lexi_bu/__init__.py
lexi_bu/__version__.py
lexi_bu/lexi.py
lexi_bu/tests/__init__.py
lexi_bu/tests/test_lexi.py
lexi_bu-0.3.4.dist-info/LICENSE
lexi_bu-0.3.4.dist-info/METADATA
lexi_bu-0.3.4.dist-info/WHEEL
lexi_bu-0.3.4.dist-info/RECORD
