Metadata-Version: 2.1
Name: lexi_bu
Version: 0.3.4
Summary: A python package for data analysis related to LEXI
Home-page: https://lexi-bu.github.io/
License: GNU GPLv3
Author: qudsiramiz
Author-email: qudsiramiz@gmail.com
Maintainer: Brian Walsh
Maintainer-email: bwalsh@bu.edu
Requires-Python: >=3.9
Classifier: License :: Other/Proprietary License
Classifier: Programming Language :: Python :: 3
Classifier: Programming Language :: Python :: 3.9
Classifier: Programming Language :: Python :: 3.10
Classifier: Programming Language :: Python :: 3.11
Classifier: Programming Language :: Python :: 3.12
Classifier: Programming Language :: Python :: 3.13
Requires-Dist: cdflib (>=1.2.3,<2.0.0)
Requires-Dist: jupyter (>=1.0.0,<2.0.0)
Requires-Dist: matplotlib (>=3.8.2,<4.0.0)
Requires-Dist: pandas (>=2.2.0,<3.0.0)
Requires-Dist: pytest (>=8.0.0,<9.0.0)
Requires-Dist: toml (>=0.10.2,<0.11.0)
Project-URL: Documentation, https://lexi-bu.github.io/lexi
Project-URL: Repository, https://github.com/Lexi-BU/lexi
